dinkit/__init__.py
dinkit/__version__.py
dinkit/dinkit.dll
dinkit/dinkit.py
dinkit/libdinkit.dylib
dinkit/libdinkit.so
dinkit/test.py
dinkit-1.1.1.dist-info/LICENSE
dinkit-1.1.1.dist-info/METADATA
dinkit-1.1.1.dist-info/WHEEL
dinkit-1.1.1.dist-info/top_level.txt
dinkit-1.1.1.dist-info/RECORD
