Metadata-Version: 2.1
Name: dinkit
Version: 1.1.1
Summary: Digital Ink Kit
Author: liutingchao
Author-email: liutingchao@hotmail.com
License: MIT
Classifier: Development Status :: 5 - Production/Stable
Classifier: License :: OSI Approved :: MIT License
Classifier: Operating System :: Microsoft :: Windows
Classifier: Operating System :: POSIX :: Linux
Classifier: Intended Audience :: Developers
Classifier: Programming Language :: Python :: 3
Requires-Python: >=3.6
License-File: LICENSE
Requires-Dist: pywin32 ; platform_system == "Windows"
